isulapy/__init__.py
isulapy/api_pb2.py
isulapy/api_pb2_grpc.py
isulapy/isula.py
isulapy-0.0.2.dist-info/LICENSE
isulapy-0.0.2.dist-info/METADATA
isulapy-0.0.2.dist-info/WHEEL
isulapy-0.0.2.dist-info/top_level.txt
isulapy-0.0.2.dist-info/RECORD
